aulos/__init__.py
aulos/__main__.py
aulos/_errors.py
aulos/_warnings.py
aulos/TET12/__init__.py
aulos/TET12/chord.py
aulos/TET12/key.py
aulos/TET12/mode.py
aulos/TET12/note.py
aulos/TET12/pitchclass.py
aulos/TET12/scale.py
aulos/TET12/tuner.py
aulos/TET12/utils.py
aulos/TET24/__init__.py
aulos/_core/__init__.py
aulos/_core/object.py
aulos/_core/schema.py
aulos/_core/setting.py
aulos/_core/chord/__init__.py
aulos/_core/chord/quality.py
aulos/_core/chord/bases/__init__.py
aulos/_core/chord/bases/chord.py
aulos/_core/chord/schemas/__init__.py
aulos/_core/chord/schemas/chord.py
aulos/_core/context/__init__.py
aulos/_core/context/context.py
aulos/_core/context/inject.py
aulos/_core/mode/__init__.py
aulos/_core/mode/bases/__init__.py
aulos/_core/mode/bases/mode.py
aulos/_core/mode/schemas/__init__.py
aulos/_core/mode/schemas/mode.py
aulos/_core/note/__init__.py
aulos/_core/note/note.py
aulos/_core/note/bases/__init__.py
aulos/_core/note/bases/note.py
aulos/_core/note/schemas/__init__.py
aulos/_core/note/schemas/note.py
aulos/_core/pitch/__init__.py
aulos/_core/pitch/bases/__init__.py
aulos/_core/pitch/schemas/__init__.py
aulos/_core/pitch/schemas/pitch.py
aulos/_core/pitchclass/__init__.py
aulos/_core/pitchclass/pitchclass.py
aulos/_core/pitchclass/bases/__init__.py
aulos/_core/pitchclass/bases/key.py
aulos/_core/pitchclass/bases/pitchclass.py
aulos/_core/pitchclass/schemas/__init__.py
aulos/_core/pitchclass/schemas/key.py
aulos/_core/pitchclass/schemas/pitchclass.py
aulos/_core/scale/__init__.py
aulos/_core/scale/diatonic.py
aulos/_core/scale/bases/__init__.py
aulos/_core/scale/bases/scale.py
aulos/_core/scale/schemas/__init__.py
aulos/_core/scale/schemas/scale.py
aulos/_core/tuner/__init__.py
aulos/_core/tuner/bases/__init__.py
aulos/_core/tuner/bases/tuner.py
aulos/_core/tuner/schemas/__init__.py
aulos/_core/tuner/schemas/tuner.py
aulos/_core/utils/__init__.py
aulos/_core/utils/dataclass.py
aulos/_core/utils/intervals.py
aulos/_core/utils/positions.py
aulos-0.1.3.dist-info/METADATA
aulos-0.1.3.dist-info/WHEEL
aulos-0.1.3.dist-info/entry_points.txt
aulos-0.1.3.dist-info/licenses/LICENSE
aulos-0.1.3.dist-info/RECORD
