Metadata-Version: 2.4
Name: aulos
Version: 0.1.3
Summary: Python library for speech processing and analysis from a music theory perspective.
Project-URL: Homepage, https://github.com/Oujox/aulos
Project-URL: Repository, https://github.com/Oujox/aulos
License: MIT License
License-File: LICENSE
Classifier: Operating System :: OS Independent
Classifier: Programming Language :: Python :: 3
Classifier: Programming Language :: Python :: 3 :: Only
Classifier: Programming Language :: Python :: 3.12
Classifier: Programming Language :: Python :: 3.13
Classifier: Topic :: Multimedia :: Sound/Audio :: Analysis
Classifier: Typing :: Typed
Requires-Python: >=3.12
